Workbook

Sheet Portada
A1: KIT ANTES DE EMPRENDER
A2: Plantillas financieras y fiscales para revisar antes de iniciar un negocio
A4: Convención de colores: | B4: Azul = captura del usuario | D4: Negro = fórmula | F4: Verde = dato vinculado | H4: Naranja = revisar
A6: Este archivo acompaña el ebook, minicurso grabado y asesoría personalizada. Llena primero las celdas azules y revisa los resultados calculados automáticamente.
A8: Hojas incluidas
A9: Hoja | B9: Para qué sirve | C9: Resultado esperado
A10: Diagnóstico | B10: Aterriza idea, cliente, actividad, riesgos y preparación fiscal. | C10: Decidir si la idea está lista para validarse.
A11: Inversión Inicial | B11: Calcula gastos de arranque y colchón de supervivencia. | C11: Saber cuánto necesitas antes de depender del negocio.
A12: Punto Equilibrio | B12: Calcula ventas/servicios mínimos para cubrir gastos. | C12: Definir metas mínimas de ventas.
A13: Precio Servicios | B13: Calcula precio mínimo, recomendado y premium. | C13: Evitar competir solo por precio.
A14: Control Mensual | B14: Da seguimiento a ingresos, gastos, impuestos y utilidad. | C14: Tomar decisiones mensuales con datos.
A15: Checklist Fiscal | B15: Organiza dudas y documentos para asesoría fiscal. | C15: Llegar mejor preparado al contador/asesor.
A16: Asesoría Previa | B16: Resumen para enviar antes de la sesión personalizada. | C16: Hacer la asesoría más productiva.
A19: Fuentes y notas
A20: SAT - Actividades empresariales y profesionales | B20: https://www.sat.gob.mx/portal/public/personas-fisicas/pf-actividades-empresariales-y-profesionales
A21: SAT - Regímenes fiscales para emprendedores | B21: https://wwwmat.sat.gob.mx/consulta/09788/emprendedor,-conoce-los-regimenes-fiscales-de-las-personas-fisicas
A22: Cámara de Diputados - Ley del IVA | B22: http://www.diputados.gob.mx/LeyesBiblio/pdf/LIVA.pdf
A23: Cámara de Diputados - Ley del ISR | B23: https://www.diputados.gob.mx/LeyesBiblio/ref/lisr.htm
A24: Conseri | B24: https://www.conseri.mx/
A26: Aviso: estas plantillas son educativas y no sustituyen asesoría fiscal, contable, legal o financiera personalizada. Valida régimen, obligaciones e impuestos con un especialista antes de operar o emitir CFDI recurrentes.

Sheet Diagnóstico
A1: Diagnóstico antes de emprender
A2: Completa la información base para evaluar claridad, riesgos y preparación inicial
A4: Convención de colores: | B4: Azul = captura del usuario | D4: Negro = fórmula | F4: Verde = dato vinculado | H4: Naranja = revisar
A6: Datos del proyecto
A7: Campo | B7: Captura | C7: Estado | D7: Comentario
A8: Nombre del proyecto | B8: Despacho CONSERI | C8: Listo
A9: Actividad principal | B9: Asesoría contable, fiscal y financiera | C9: Listo
A10: Cliente ideal | B10: Emprendedores y pequeños negocios de habla hispana | C10: Listo
A11: País/base fiscal de referencia | B11: México | C11: Revisar | D11: Adaptar si se vende fuera de México
A12: Problema que resuelve | B12: Falta de claridad financiera y fiscal antes de emprender | C12: Listo
A13: Oferta inicial | B13: Servicio integral contable y fiscal | C13: Listo
A16: Semáforo de preparación
A17: Área | B17: Pregunta | C17: Respuesta | D17: Puntaje | E17: Interpretación | F17: Acción sugerida
A18: Idea | B18: ¿Puedo explicar qué vendo en una frase? | C18: Sí | D18: =IF(C18="Sí",1,IF(C18="Parcial",0.5,0)) -> 1 | E18: =IF(D18=1,"Listo",IF(D18=0.5,"Revisar","Prioridad")) -> Listo | F18: =IF(D18=1,"Mantener",IF(D18=0.5,"Ajustar","Resolver antes de lanzar")) -> Mantener
A19: Cliente | B19: ¿Sé exactamente a quién quiero vender? | C19: Sí | D19: =IF(C19="Sí",1,IF(C19="Parcial",0.5,0)) -> 1 | E19: =IF(D19=1,"Listo",IF(D19=0.5,"Revisar","Prioridad")) -> Listo | F19: =IF(D19=1,"Mantener",IF(D19=0.5,"Ajustar","Resolver antes de lanzar")) -> Mantener
A20: Precio | B20: ¿Tengo precio mínimo y recomendado calculado? | C20: Sí | D20: =IF(C20="Sí",1,IF(C20="Parcial",0.5,0)) -> 1 | E20: =IF(D20=1,"Listo",IF(D20=0.5,"Revisar","Prioridad")) -> Listo | F20: =IF(D20=1,"Mantener",IF(D20=0.5,"Ajustar","Resolver antes de lanzar")) -> Mantener
A21: Costos | B21: ¿Conozco mis gastos fijos y costos variables? | C21: Sí | D21: =IF(C21="Sí",1,IF(C21="Parcial",0.5,0)) -> 1 | E21: =IF(D21=1,"Listo",IF(D21=0.5,"Revisar","Prioridad")) -> Listo | F21: =IF(D21=1,"Mantener",IF(D21=0.5,"Ajustar","Resolver antes de lanzar")) -> Mantener
A22: Flujo | B22: ¿Sé cuántos meses puedo resistir? | C22: Parcial | D22: =IF(C22="Sí",1,IF(C22="Parcial",0.5,0)) -> 0.5 | E22: =IF(D22=1,"Listo",IF(D22=0.5,"Revisar","Prioridad")) -> Revisar | F22: =IF(D22=1,"Mantener",IF(D22=0.5,"Ajustar","Resolver antes de lanzar")) -> Ajustar
A23: Fiscal | B23: ¿Validé régimen y obligaciones con asesoría? | C23: Sí | D23: =IF(C23="Sí",1,IF(C23="Parcial",0.5,0)) -> 1 | E23: =IF(D23=1,"Listo",IF(D23=0.5,"Revisar","Prioridad")) -> Listo | F23: =IF(D23=1,"Mantener",IF(D23=0.5,"Ajustar","Resolver antes de lanzar")) -> Mantener
A24: Venta | B24: ¿Tengo canal inicial para conseguir prospectos? | C24: No | D24: =IF(C24="Sí",1,IF(C24="Parcial",0.5,0)) -> 0 | E24: =IF(D24=1,"Listo",IF(D24=0.5,"Revisar","Prioridad")) -> Prioridad | F24: =IF(D24=1,"Mantener",IF(D24=0.5,"Ajustar","Resolver antes de lanzar")) -> Resolver antes de lanzar
A25: Operación | B25: ¿Tengo proceso o checklist de entrega? | C25: Parcial | D25: =IF(C25="Sí",1,IF(C25="Parcial",0.5,0)) -> 0.5 | E25: =IF(D25=1,"Listo",IF(D25=0.5,"Revisar","Prioridad")) -> Revisar | F25: =IF(D25=1,"Mantener",IF(D25=0.5,"Ajustar","Resolver antes de lanzar")) -> Ajustar
A28: Resultado diagnóstico
A29: Puntaje total | B29: =SUM(D18:D25) -> 6
A30: Porcentaje de preparación | B30: =B29/COUNTA(A18:A25) -> 0.75
A31: Veredicto | B31: =IF(B30>=0.8,"Listo para validar",IF(B30>=0.5,"Validar con ajustes","No lanzar todavía")) -> Validar con ajustes

Sheet Inversión Inicial
A1: Inversión inicial y colchón
A2: Calcula cuánto necesitas para arrancar y sobrevivir los primeros meses
A4: Convención de colores: | B4: Azul = captura del usuario | D4: Negro = fórmula | F4: Verde = dato vinculado | H4: Naranja = revisar
A6: Supuestos generales
A7: Meses de colchón objetivo | B7: 3
A8: Gasto personal mensual básico | B8: 18000
A9: Reserva fiscal provisional sobre cobros | B9: 0.2
A12: Inversión inicial
A13: Concepto | B13: Indispensable | C13: Monto estimado | D13: Cuándo compra | E13: Fuente/nota | F13: Prioridad
A14: Equipo de cómputo | B14: Sí | C14: 18000 | D14: Antes de iniciar | E14: Cotización o equipo actual | F14: Alta
A15: Software y herramientas | B15: Sí | C15: 4000 | D15: Antes de iniciar | E15: Licencias requeridas | F15: Alta
A16: Dominio / página / marca básica | B16: Sí | C16: 8000 | D16: Primer mes | E16: Presencia mínima viable | F16: Media
A17: Publicidad de lanzamiento | B17: Sí | C17: 6000 | D17: Primer mes | E17: Presupuesto de validación | F17: Alta
A18: Capacitación inicial | B18: Sí | C18: 5000 | D18: Primer mes | E18: Actualización técnica | F18: Media
A19: Asesoría legal/fiscal inicial | B19: Sí | C19: 4000 | D19: Antes de facturar | E19: Validación de régimen/contratos | F19: Alta
A20: Papelería/plantillas/formato | B20: No | C20: 2000 | D20: Después | E20: Puede iniciar en versión básica | F20: Baja
A22: Total inversión inicial | C22: =SUM(C14:C20) -> 47000
A25: Gastos fijos mensuales del negocio
A26: Concepto | B26: Monto mensual | C26: ¿Reducible? | D26: Comentario | E26: Estado | F26: Acción
A27: Software y herramientas | B27: 2500 | C27: Parcial | D27: Revisar licencias duplicadas | E27: Activo | F27: Optimizar
A28: Internet, teléfono y nube | B28: 1500 | C28: No | D28: Necesario para operación | E28: Activo | F28: Mantener
A29: Publicidad y contenido | B29: 3000 | C29: Sí | D29: Medir generación de prospectos | E29: Activo | F29: Medir ROI
A30: Capacitación promedio | B30: 2000 | C30: Parcial | D30: Necesaria en temas fiscales | E30: Activo | F30: Priorizar
A31: Apoyo externo eventual | B31: 4000 | C31: Sí | D31: Usarlo si libera tiempo | E31: Variable | F31: Controlar
A32: Gastos administrativos varios | B32: 2000 | C32: Sí | D32: Evitar fugas pequeñas | E32: Activo | F32: Reducir
A34: Total gastos fijos del negocio | B34: =SUM(B27:B32) -> 15000
A37: Colchón de supervivencia
A38: Presión mensual total | B38: =B34+B8 -> 33000
A39: Colchón sugerido | B39: =B38*B7 -> 99000
A40: Total para arrancar + colchón | B40: =C22+B39 -> 146000

Sheet Punto Equilibrio
A1: Punto de equilibrio
A2: Calcula cuántos productos, servicios o clientes necesitas para no perder
A4: Convención de colores: | B4: Azul = captura del usuario | D4: Negro = fórmula | F4: Verde = dato vinculado | H4: Naranja = revisar
A6: Supuestos vinculados
A7: Gastos fijos mensuales | B7: ='Inversión Inicial'!B34 -> 15000
A8: Gasto personal del emprendedor | B8: ='Inversión Inicial'!B8 -> 18000
A9: Meta utilidad adicional | B9: 0
A12: Productos o servicios
A13: Servicio/Producto | B13: Precio unitario | C13: Costo variable | D13: Margen unitario | E13: Margen % | F13: Unidades para cubrir negocio | G13: Unidades para cubrir negocio + vida
A14: Contabilidad mensual básica | B14: 3000 | C14: 1000 | D14: =B14-C14 -> 2000 | E14: =IFERROR(D14/B14,0) -> 0.66666667 | F14: =IFERROR(ROUNDUP($B$7/D14,0),0) -> 8 | G14: =IFERROR(ROUNDUP(($B$7+$B$8+$B$9)/D14,0),0) -> 17
A15: Asesoría fiscal puntual | B15: 2500 | C15: 600 | D15: =B15-C15 -> 1900 | E15: =IFERROR(D15/B15,0) -> 0.76 | F15: =IFERROR(ROUNDUP($B$7/D15,0),0) -> 8 | G15: =IFERROR(ROUNDUP(($B$7+$B$8+$B$9)/D15,0),0) -> 18
A16: Regularización simple | B16: 6000 | C16: 2000 | D16: =B16-C16 -> 4000 | E16: =IFERROR(D16/B16,0) -> 0.66666667 | F16: =IFERROR(ROUNDUP($B$7/D16,0),0) -> 4 | G16: =IFERROR(ROUNDUP(($B$7+$B$8+$B$9)/D16,0),0) -> 9
A17: Diagnóstico financiero inicial | B17: 4500 | C17: 1200 | D17: =B17-C17 -> 3300 | E17: =IFERROR(D17/B17,0) -> 0.73333333 | F17: =IFERROR(ROUNDUP($B$7/D17,0),0) -> 5 | G17: =IFERROR(ROUNDUP(($B$7+$B$8+$B$9)/D17,0),0) -> 10
A18: Contabilidad mensual PF | B18: 696 | C18: 196 | D18: =B18-C18 -> 500 | E18: =IFERROR(D18/B18,0) -> 0.7183908 | F18: =IFERROR(ROUNDUP($B$7/D18,0),0) -> 30 | G18: =IFERROR(ROUNDUP(($B$7+$B$8+$B$9)/D18,0),0) -> 66
A21: Resumen
A22: Margen promedio unitario | B22: =AVERAGE(D14:D18) -> 2340
A23: Unidades promedio para cubrir negocio | B23: =ROUNDUP(B7/B22,0) -> 7
A24: Unidades promedio para cubrir negocio + vida | B24: =ROUNDUP((B7+B8+B9)/B22,0) -> 15

Sheet Precio Servicios
A1: Calculadora de precio
A2: Construye precio mínimo, recomendado y premium
A4: Convención de colores: | B4: Azul = captura del usuario | D4: Negro = fórmula | F4: Verde = dato vinculado | H4: Naranja = revisar
A6: Supuestos generales
A7: Horas disponibles facturables al mes | B7: 80
A8: Gastos fijos mensuales | B8: ='Inversión Inicial'!B34 -> 15000
A9: Reserva fiscal provisional | B9: ='Inversión Inicial'!B9 -> 0.2
A10: Margen objetivo | B10: 0.25
A13: Servicios
A14: Servicio | B14: Horas entrega | C14: Costo directo | D14: Valor hora | E14: Parte gastos fijos | F14: Reserva fiscal | G14: Precio mínimo | H14: Precio recomendado | I14: Precio premium
A15: Contabilidad mensual básica | B15: 4 | C15: 1000 | D15: 350 | E15: =($B$8/$B$7)*B15 -> 750 | F15: =(C15+D15*B15+E15)*$B$9/(1-$B$9) -> 787.5 | G15: =C15+D15*B15+E15+F15 -> 3937.5 | H15: =G15/(1-$B$10) -> 5250 | I15: =H15*1.5 -> 7875
A16: Asesoría fiscal puntual | B16: 2 | C16: 500 | D16: 500 | E16: =($B$8/$B$7)*B16 -> 375 | F16: =(C16+D16*B16+E16)*$B$9/(1-$B$9) -> 468.75 | G16: =C16+D16*B16+E16+F16 -> 2343.75 | H16: =G16/(1-$B$10) -> 3125 | I16: =H16*1.5 -> 4687.5
A17: Regularización simple | B17: 8 | C17: 3000 | D17: 450 | E17: =($B$8/$B$7)*B17 -> 1500 | F17: =(C17+D17*B17+E17)*$B$9/(1-$B$9) -> 2025 | G17: =C17+D17*B17+E17+F17 -> 10125 | H17: =G17/(1-$B$10) -> 13500 | I17: =H17*1.5 -> 20250
A18: Diagnóstico financiero inicial | B18: 5 | C18: 1500 | D18: 500 | E18: =($B$8/$B$7)*B18 -> 937.5 | F18: =(C18+D18*B18+E18)*$B$9/(1-$B$9) -> 1234.375 | G18: =C18+D18*B18+E18+F18 -> 6171.875 | H18: =G18/(1-$B$10) -> 8229.1667 | I18: =H18*1.5 -> 12343.75
A21: Paquetes sugeridos
A22: Paquete | B22: Precio | C22: Incluye | D22: Cliente ideal | E22: Nota
A23: Básico | B23: =H15 -> 5250 | C23: Cumplimiento mínimo + recordatorios | D23: Emprendedor con operación simple | E23: Evitar alcance excesivo
A24: Integral | B24: =H15+H16 -> 8375 | C24: Revisión mensual + asesoría puntual | D24: Negocio que requiere decisiones | E24: Mejor opción
A25: Premium | B25: =I15+H16 -> 11000 | C25: Prioridad + indicadores + seguimiento | D25: Cliente con mayor complejidad | E25: Validar capacidad

Sheet Control Mensual
A1: Control mensual
A2: Registra ingresos, gastos, impuestos y utilidad estimada cada mes
A4: Convención de colores: | B4: Azul = captura del usuario | D4: Negro = fórmula | F4: Verde = dato vinculado | H4: Naranja = revisar
A6: Captura mensual
A7: Concepto | B7: Ene | C7: Feb | D7: Mar | E7: Abr | F7: May | G7: Jun | H7: Jul | I7: Ago | J7: Sep | K7: Oct | L7: Nov | M7: Dic | N7: Total/Prom.
A8: Ingresos cobrados | B8: 80000 | C8: 80000 | D8: 120000 | E8: 80000 | F8: 80000 | G8: 80000 | H8: 80000 | I8: 80000 | J8: 80000 | K8: 80000 | L8: 80000 | M8: 80000 | N8: =SUM(B8:M8) -> 1000000
A9: Costos variables | B9: =B8*40% -> 32000 | C9: =C8*40% -> 32000 | D9: =D8*40% -> 48000 | E9: =E8*40% -> 32000 | F9: =F8*40% -> 32000 | G9: =G8*40% -> 32000 | H9: =H8*40% -> 32000 | I9: =I8*40% -> 32000 | ... M9: =M8*40% -> 32000 | N9: =SUM(B9:M9) -> 400000
A10: Gastos fijos | B10: 15000 | C10: 15000 | D10: 15000 | E10: 15000 | F10: 15000 | G10: 15000 | H10: 15000 | I10: 15000 | J10: 15000 | K10: 15000 | L10: 15000 | M10: 15000 | N10: =SUM(B10:M10) -> 180000
A11: Reserva impuestos | B11: =B8*10% -> 8000 | C11: =C8*10% -> 8000 | D11: =D8*10% -> 12000 | E11: =E8*10% -> 8000 | F11: =F8*10% -> 8000 | G11: =G8*10% -> 8000 | H11: =H8*10% -> 8000 | I11: =I8*10% -> 8000 | ... M11: =M8*10% -> 8000 | N11: =SUM(B11:M11) -> 100000
A12: Pago dueño | B12: 18000 | C12: 18000 | D12: 18000 | E12: 18000 | F12: 18000 | G12: 18000 | H12: 18000 | I12: 18000 | J12: 18000 | K12: 18000 | L12: 18000 | M12: 18000 | N12: =SUM(B12:M12) -> 216000
A13: Otros gastos | B13: 500 | C13: 500 | D13: 500 | E13: 500 | F13: 500 | G13: 500 | H13: 500 | I13: 500 | J13: 500 | K13: 500 | L13: 500 | M13: 500 | N13: =SUM(B13:M13) -> 6000
A14: Utilidad estimada | B14: =B8-B9-B10-B11-B12-B13 -> 6500 | C14: =C8-C9-C10-C11-C12-C13 -> 6500 | D14: =D8-D9-D10-D11-D12-D13 -> 26500 | E14: =E8-E9-E10-E11-E12-E13 -> 6500 | F14: =F8-F9-F10-F11-F12-F13 -> 6500 | G14: =G8-G9-G10-G11-G12-G13 -> 6500 | H14: =H8-H9-H10-H11-H12-H13 -> 6500 | I14: =I8-I9-I10-I11-I12-I13 -> 6500 | ... M14: =M8-M9-M10-M11-M12-M13 -> 6500 | N14: =SUM(B14:M14) -> 98000
A15: Margen utilidad | B15: =IFERROR(B14/B8,0) -> 0.08125 | C15: =IFERROR(C14/C8,0) -> 0.08125 | D15: =IFERROR(D14/D8,0) -> 0.22083333 | E15: =IFERROR(E14/E8,0) -> 0.08125 | F15: =IFERROR(F14/F8,0) -> 0.08125 | G15: =IFERROR(G14/G8,0) -> 0.08125 | H15: =IFERROR(H14/H8,0) -> 0.08125 | I15: =IFERROR(I14/I8,0) -> 0.08125 | ... M15: =IFERROR(M14/M8,0) -> 0.08125 | N15: =AVERAGE(B15:M15) -> 0.092881944
A16: Cuentas por cobrar | B16: =B8*1% -> 800 | C16: =C8*1% -> 800 | D16: =D8*1% -> 1200 | E16: =E8*1% -> 800 | F16: =F8*1% -> 800 | G16: =G8*1% -> 800 | H16: =H8*1% -> 800 | I16: =I8*1% -> 800 | ... M16: =M8*1% -> 800 | N16: =M16 -> 800
A19: Total anual

Sheet Checklist Fiscal
A1: Checklist fiscal antes de operar
A2: Organiza información para revisar régimen, obligaciones y documentos
A4: Convención de colores: | B4: Azul = captura del usuario | D4: Negro = fórmula | F4: Verde = dato vinculado | H4: Naranja = revisar
A6: Preguntas fiscales básicas
A7: Área | B7: Pregunta | C7: Estado | D7: Notas
A8: Actividad | B8: ¿La actividad económica está descrita con claridad? | C8: Pendiente
A9: Régimen | B9: ¿Se validó si conviene RESICO, actividad empresarial/profesional u otro? | C9: Pendiente
A10: IVA | B10: ¿La operación causa IVA o existen exenciones/no objeto? | C10: Pendiente
A11: Retenciones | B11: ¿Los clientes harán retenciones? | C11: Pendiente
A12: CFDI | B12: ¿Se definió concepto, clave de producto/servicio y uso frecuente? | C12: Pendiente
A13: Deducciones | B13: ¿Se tienen identificados gastos y CFDI deducibles? | C13: Pendiente
A14: Declaraciones | B14: ¿Se calendarizaron obligaciones mensuales/anuales? | C14: Pendiente
A15: Cuenta bancaria | B15: ¿Se separó cuenta del negocio y personal? | C15: Pendiente
A16: Contratos | B16: ¿Existe contrato o propuesta de servicio? | C16: Pendiente
A19: Fuentes útiles
A20: SAT - Actividades empresariales y profesionales | B20: https://www.sat.gob.mx/portal/public/personas-fisicas/pf-actividades-empresariales-y-profesionales
A21: SAT - Regímenes personas físicas | B21: https://wwwmat.sat.gob.mx/consulta/09788/emprendedor,-conoce-los-regimenes-fiscales-de-las-personas-fisicas
A22: Ley IVA Cámara de Diputados | B22: http://www.diputados.gob.mx/LeyesBiblio/pdf/LIVA.pdf
A23: Ley ISR Cámara de Diputados | B23: https://www.diputados.gob.mx/LeyesBiblio/ref/lisr.htm

Sheet Asesoría Previa
A1: Resumen para asesoría personalizada
A2: Completa esta hoja antes de tu sesión de diagnóstico
A4: Convención de colores: | B4: Azul = captura del usuario | D4: Negro = fórmula | F4: Verde = dato vinculado | H4: Naranja = revisar
A6: Resumen ejecutivo
A7: Tema | B7: Respuesta / dato vinculado | C7: Estado | D7: Prioridad | E7: Comentario para asesoría
A8: Proyecto / actividad | B8: =Diagnóstico!B9 -> Asesoría contable, fiscal y financiera | C8: Listo | D8: Alta
A9: Cliente ideal | B9: =Diagnóstico!B10 -> Emprendedores y pequeños negocios de habla hispana | C9: Listo | D9: Alta
A10: Oferta inicial | B10: =Diagnóstico!B13 -> Servicio integral contable y fiscal | C10: Listo | D10: Media
A11: Puntaje diagnóstico | B11: =Diagnóstico!B30 -> 0.75 | C11: Revisar | D11: Alta
A12: Inversión inicial | B12: ='Inversión Inicial'!C22 -> 47000 | C12: Revisar | D12: Alta
A13: Colchón sugerido | B13: ='Inversión Inicial'!B39 -> 99000 | C13: Revisar | D13: Alta
A14: Gasto fijo mensual | B14: ='Inversión Inicial'!B34 -> 15000 | C14: Revisar | D14: Alta
A15: Unidades para cubrir negocio | B15: ='Punto Equilibrio'!B23 -> 7 | C15: Revisar | D15: Alta
A16: Unidades para cubrir negocio + vida | B16: ='Punto Equilibrio'!B24 -> 15 | C16: Revisar | D16: Alta
A20: Preguntas para la asesoría
A21: Pregunta | B21: Detalle | C21: Prioridad | D21: Respuesta durante asesoría | E21: Acción posterior
A22: ¿Qué régimen fiscal puede corresponderme? | C22: Alta
A23: ¿Estoy considerando correctamente IVA, ISR o retenciones? | C23: Alta
A24: ¿Mis precios cubren costos, impuestos y margen? | C24: Alta
A25: ¿Qué documentos debo conservar desde el inicio? | C25: Media
A26: ¿Qué plantilla debo revisar cada mes? | C26: Media
